ricebowl/__init__.py
ricebowl/images.py
ricebowl/preprocessing.py
ricebowl-1.0.0.dist-info/LICENSE
ricebowl-1.0.0.dist-info/METADATA
ricebowl-1.0.0.dist-info/WHEEL
ricebowl-1.0.0.dist-info/top_level.txt
ricebowl-1.0.0.dist-info/RECORD
