Metadata-Version: 2.1
Name: ricebowl
Version: 1.0.0
Summary: This package allows the users to preprocess dataframes, images and then use ml models using a single command
Home-page: https://github.com/shivekchhabra/ricebowl
Author: Shivek Chhabra
Author-email: shivekchhabra@gmail.com
License: UNKNOWN
Platform: UNKNOWN
Classifier: Programming Language :: Python :: 3
Classifier: License :: OSI Approved :: MIT License
Classifier: Operating System :: OS Independent
